RTL/aes256_addroundkey.v
//==============================================================================
// File: aes256_addroundkey.v
// Description: AddRoundKey Transformation for AES-256
// - XOR state with round key
// - Same operation for both encryption and decryption
// - Combinational logic (no registers)
//==============================================================================

module aes256_addroundkey (
    input  wire [127:0] state_i,     // Input state (16 bytes)
    input  wire [127:0] round_key_i, // Round key (16 bytes)
    output wire [127:0] state_o      // Output state (16 bytes)
);

    //==========================================================================
    // ADDROUNDKEY TRANSFORMATION
    // Simple XOR operation: state XOR round_key
    //==========================================================================
    assign state_o = state_i ^ round_key_i;

endmodule

tb_aes256/tb_aes256_addroundkey.v
//==============================================================================
// File: tb_aes256_addroundkey.v
// Description: Comprehensive testbench for aes256_addroundkey module
// Tests:
//   - Basic XOR functionality
//   - Identity property: AddRoundKey(AddRoundKey(state, key), key) = state
//   - Zero key/state cases
//   - FIPS-197 test vectors
//   - Random patterns
//   - Bitwise independence
//==============================================================================

`timescale 1ns/1ps

module tb_aes256_addroundkey;

    //==========================================================================
    // TESTBENCH SIGNALS
    //==========================================================================
    reg  [127:0] state_in;
    reg  [127:0] round_key;
    wire [127:0] state_out;
    
    integer errors;
    integer test_count;

    //==========================================================================
    // DUT INSTANTIATION
    //==========================================================================
    aes256_addroundkey dut (
        .state_i(state_in),
        .round_key_i(round_key),
        .state_o(state_out)
    );

    //==========================================================================
    // HELPER FUNCTIONS
    //==========================================================================
    
    // Extract byte from 128-bit value
    function [7:0] get_byte;
        input [127:0] data;
        input integer byte_index;
        begin
            get_byte = data[byte_index*8 +: 8];
        end
    endfunction

    // Display state as 4x4 matrix
    task display_state_matrix;
        input [255:0] label;
        input [127:0] state;
        integer r, c, idx;
        begin
            $display("%s:", label);
            for (r = 0; r < 4; r = r + 1) begin
                $write("  ");
                for (c = 0; c < 4; c = c + 1) begin
                    idx = c * 4 + r;
                    $write("%02h ", get_byte(state, idx));
                end
                $display("");
            end
        end
    endtask

    //==========================================================================
    // TEST TASKS
    //==========================================================================
    
    task check_addroundkey;
        input [255:0] test_name;
        input [127:0] test_state;
        input [127:0] test_key;
        reg [127:0] expected;
        integer i;
        begin
            test_count = test_count + 1;
            state_in = test_state;
            round_key = test_key;
            expected = test_state ^ test_key;  // Expected is simple XOR
            
            #10;  // Wait for combinational logic
            
            if (state_out !== expected) begin
                $display("FAIL [Test %0d]: %s", test_count, test_name);
                display_state_matrix("  Input State", test_state);
                display_state_matrix("  Round Key", test_key);
                display_state_matrix("  Expected", expected);
                display_state_matrix("  Got", state_out);
                
                // Show bit-level differences
                for (i = 0; i < 16; i = i + 1) begin
                    if (get_byte(state_out, i) !== get_byte(expected, i)) begin
                        $display("  Byte %0d mismatch: expected %02h, got %02h", 
                                 i, get_byte(expected, i), get_byte(state_out, i));
                    end
                end
                
                errors = errors + 1;
            end else begin
                $display("PASS [Test %0d]: %s", test_count, test_name);
            end
        end
    endtask

    task check_identity_property;
        input [255:0] test_name;
        input [127:0] original_state;
        input [127:0] test_key;
        reg [127:0] after_first_xor;
        reg [127:0] after_second_xor;
        begin
            test_count = test_count + 1;
            
            // First AddRoundKey
            state_in = original_state;
            round_key = test_key;
            #10;
            after_first_xor = state_out;
            
            // Second AddRoundKey with same key
            state_in = after_first_xor;
            round_key = test_key;
            #10;
            after_second_xor = state_out;
            
            // Should recover original state
            if (after_second_xor !== original_state) begin
                $display("FAIL [Test %0d]: %s", test_count, test_name);
                $display("  Identity property violated!");
                display_state_matrix("  Original State", original_state);
                display_state_matrix("  Round Key", test_key);
                display_state_matrix("  After 1st XOR", after_first_xor);
                display_state_matrix("  After 2nd XOR", after_second_xor);
                display_state_matrix("  Expected (Original)", original_state);
                errors = errors + 1;
            end else begin
                $display("PASS [Test %0d]: %s", test_count, test_name);
            end
        end
    endtask

    //==========================================================================
    // MAIN TEST SEQUENCE
    //==========================================================================
    initial begin
        $dumpfile("tb_aes256_addroundkey.vcd");
        $dumpvars(0, tb_aes256_addroundkey);
        
        errors = 0;
        test_count = 0;
        
        $display("================================================================================");
        $display("AES-256 ADDROUNDKEY TESTBENCH");
        $display("================================================================================");

        //======================================================================
        // SECTION 1: ZERO AND IDENTITY PATTERNS
        //======================================================================
        $display("\n--- Test Section 1: Zero and Identity Patterns ---");
        
        // Zero state, zero key
        check_addroundkey("Zero state, zero key", 
            128'h0, 128'h0);
        
        // Zero state, non-zero key
        check_addroundkey("Zero state, non-zero key",
            128'h0, 128'h0102030405060708090a0b0c0d0e0f10);
        
        // Non-zero state, zero key
        check_addroundkey("Non-zero state, zero key",
            128'h0102030405060708090a0b0c0d0e0f10, 128'h0);
        
        // All ones
        check_addroundkey("All ones state and key",
            128'hffffffffffffffffffffffffffffffff,
            128'hffffffffffffffffffffffffffffffff);
        
        //======================================================================
        // SECTION 2: FIPS-197 TEST VECTORS
        //======================================================================
        $display("\n--- Test Section 2: FIPS-197 Test Vectors ---");
        
        // FIPS-197 Appendix B - Initial AddRoundKey (Round 0)
        // Plaintext: 00112233445566778899aabbccddeeff
        // Key (first 16 bytes): 000102030405060708090a0b0c0d0e0f
        check_addroundkey("FIPS-197 Appendix B - Round 0",
            128'h00112233445566778899aabbccddeeff,
            128'h000102030405060708090a0b0c0d0e0f);
        // Expected: 00102030405060708090a0b0c0d0e0f0
        
        // FIPS-197 Appendix C.3 - Round 1 AddRoundKey
        // State after MixColumns: 4c9adbcc2ba3b792465920f6c1da71d8 (from doc)
        // Round key: a0fafe1788542cb123a339392a6c7605
        check_addroundkey("FIPS-197 C.3 Round 1",
            128'hd8c171daf62059469227a32bccdb9a4c,
            128'h056c2a3992332a31cb2c5488e1fefa0a);
        
        //======================================================================
        // SECTION 3: IDENTITY PROPERTY TESTS
        //======================================================================
        $display("\n--- Test Section 3: Identity Property Tests ---");
        
        // AddRoundKey(AddRoundKey(state, key), key) = state
        check_identity_property("Identity - Sequential state",
            128'h0f0e0d0c0b0a09080706050403020100,
            128'h0102030405060708090a0b0c0d0e0f10);
        
        check_identity_property("Identity - FIPS-197 state",
            128'h00112233445566778899aabbccddeeff,
            128'h000102030405060708090a0b0c0d0e0f);
        
        check_identity_property("Identity - Random 1",
            128'h8e9f01c6940863a17a2c685e1db7b5c0,
            128'hffeeddccbbaa99887766554433221100);
        
        check_identity_property("Identity - All 0xFF",
            128'hffffffffffffffffffffffffffffffff,
            128'haaaaaaaa55555555aaaaaaaa55555555);
        
        check_identity_property("Identity - Alternating",
            128'haaaaaaaa55555555aaaaaaaa55555555,
            128'h5555555555555555aaaaaaaaaaaaaaaa);
        
        //======================================================================
        // SECTION 4: BIT INDEPENDENCE
        //======================================================================
        $display("\n--- Test Section 4: Bit Independence Tests ---");
        
        // Single bit in state
        check_addroundkey("Single bit in state (bit 0)",
            128'h00000000000000000000000000000001,
            128'h0);
        
        check_addroundkey("Single bit in state (bit 127)",
            128'h80000000000000000000000000000000,
            128'h0);
        
        // Single bit in key
        check_addroundkey("Single bit in key (bit 0)",
            128'h0,
            128'h00000000000000000000000000000001);
        
        check_addroundkey("Single bit in key (bit 127)",
            128'h0,
            128'h80000000000000000000000000000000);
        
        //======================================================================
        // SECTION 5: BOUNDARY VALUES
        //======================================================================
        $display("\n--- Test Section 5: Boundary Values ---");
        
        check_addroundkey("Max state, min key",
            128'hffffffffffffffffffffffffffffffff,
            128'h0);
        
        check_addroundkey("Min state, max key",
            128'h0,
            128'hffffffffffffffffffffffffffffffff);
        
        check_addroundkey("Alternating 0x55",
            128'h55555555555555555555555555555555,
            128'h55555555555555555555555555555555);
        
        check_addroundkey("Alternating 0xAA",
            128'haaaaaaaaaaaaaaaaaaaaaaaaaaaaaaaa,
            128'haaaaaaaaaaaaaaaaaaaaaaaaaaaaaaaa);
        
        //======================================================================
        // SECTION 6: RANDOM PATTERNS
        //======================================================================
        $display("\n--- Test Section 6: Random Patterns ---");
        
        check_addroundkey("Random 1",
            128'h243f6a8885a308d313198a2e03707344,
            128'ha4093822299f31d0082efa98ec4e6c89);
        
        check_addroundkey("Random 2",
            128'h452821e638d01377be5466cf34e90c6c,
            128'hc0ac29b7c97c50dd3f84d5b5b5470917);
        
        check_addroundkey("Random 3",
            128'hdeadbeefcafebabe13371337deadc0de,
            128'hfaceb00c8badf00ddeadbeefdecaf001);
        
        //======================================================================
        // SECTION 7: COMPLEMENTARY PATTERNS
        //======================================================================
        $display("\n--- Test Section 7: Complementary Patterns ---");
        
        // State and its complement
        check_addroundkey("State and complement",
            128'h0f0f0f0f0f0f0f0f0f0f0f0f0f0f0f0f,
            128'hf0f0f0f0f0f0f0f0f0f0f0f0f0f0f0f0);
        
        // Should result in all 0xFF
        check_addroundkey("Verify XOR complement = 0xFF",
            128'h12345678abcdef0fedcba98765432110,
            128'hedcba98754321f0f1234567689abcdef);
        
        //======================================================================
        // TEST SUMMARY
        //======================================================================
        $display("\n================================================================================");
        $display("Test Summary:");
        $display("  Total Tests: %0d", test_count);
        $display("  Errors:      %0d", errors);
        if (errors == 0)
            $display("  Status:      ALL TESTS PASSED ✓");
        else
            $display("  Status:      TESTS FAILED ✗");
        $display("================================================================================");
        
        $finish;
    end

endmodule

gtkwave/tb_aes256_addroundkey.vcd
$date
	Tue Nov  4 00:05:18 2025
$end
$version
	Icarus Verilog
$end
$timescale
	1ps
$end
$scope module tb_aes256_addroundkey $end
$var wire 128 ! state_out [127:0] $end
$var reg 128 " round_key [127:0] $end
$var reg 128 # state_in [127:0] $end
$var integer 32 $ errors [31:0] $end
$var integer 32 % test_count [31:0] $end
$scope function get_byte $end
$var reg 128 & data [127:0] $end
$var integer 32 ' byte_index [31:0] $end
$upscope $end
$scope module dut $end
$var wire 128 ( round_key_i [127:0] $end
$var wire 128 ) state_i [127:0] $end
$var wire 128 * state_o [127:0] $end
$upscope $end
$scope task check_addroundkey $end
$var reg 128 + expected [127:0] $end
$var reg 128 , test_key [127:0] $end
$var reg 256 - test_name [255:0] $end
$var reg 128 . test_state [127:0] $end
$var integer 32 / i [31:0] $end
$upscope $end
$scope task check_identity_property $end
$var reg 128 0 after_first_xor [127:0] $end
$var reg 128 1 after_second_xor [127:0] $end
$var reg 128 2 original_state [127:0] $end
$var reg 128 3 test_key [127:0] $end
$var reg 256 4 test_name [255:0] $end
$upscope $end
$scope task display_state_matrix $end
$var reg 256 5 label [255:0] $end
$var reg 128 6 state [127:0] $end
$var integer 32 7 c [31:0] $end
$var integer 32 8 idx [31:0] $end
$var integer 32 9 r [31:0] $end
$upscope $end
$upscope $end
$enddefinitions $end
$comment Show the parameter values. $end
$dumpall
$end
#0
$dumpvars
bx 9
bx 8
bx 7
bx 6
bx 5
bx 4
bx 3
bx 2
bx 1
bx 0
bx /
b0 .
b101101001100101011100100110111100100000011100110111010001100001011101000110010100101100001000000111101001100101011100100110111100100000011010110110010101111001 -
b0 ,
b0 +
b0 *
b0 )
b0 (
bx '
bx &
b1 %
b0 $
b0 #
b0 "
b0 !
$end
#10000
b1000000100000001100000100000001010000011000000111000010000000100100001010000010110000110000001101000011100000111100010000 !
b1000000100000001100000100000001010000011000000111000010000000100100001010000010110000110000001101000011100000111100010000 *
b1000000100000001100000100000001010000011000000111000010000000100100001010000010110000110000001101000011100000111100010000 +
b1000000100000001100000100000001010000011000000111000010000000100100001010000010110000110000001101000011100000111100010000 "
b1000000100000001100000100000001010000011000000111000010000000100100001010000010110000110000001101000011100000111100010000 (
b10 %
b1000000100000001100000100000001010000011000000111000010000000100100001010000010110000110000001101000011100000111100010000 ,
b10110100110010101110010011011110010000001110011011101000110000101110100011001010010110000100000011011100110111101101110001011010111101001100101011100100110111100100000011010110110010101111001 -
#20000
b0 "
b0 (
b1000000100000001100000100000001010000011000000111000010000000100100001010000010110000110000001101000011100000111100010000 #
b1000000100000001100000100000001010000011000000111000010000000100100001010000010110000110000001101000011100000111100010000 )
b11 %
b0 ,
b1000000100000001100000100000001010000011000000111000010000000100100001010000010110000110000001101000011100000111100010000 .
b10011100110111101101110001011010111101001100101011100100110111100100000011100110111010001100001011101000110010100101100001000000111101001100101011100100110111100100000011010110110010101111001 -
#30000
b0 !
b0 *
b0 +
b11111111111111111111111111111111111111111111111111111111111111111111111111111111111111111111111111111111111111111111111111111111 "
b11111111111111111111111111111111111111111111111111111111111111111111111111111111111111111111111111111111111111111111111111111111 (
b11111111111111111111111111111111111111111111111111111111111111111111111111111111111111111111111111111111111111111111111111111111 #
b11111111111111111111111111111111111111111111111111111111111111111111111111111111111111111111111111111111111111111111111111111111 )
b100 %
b11111111111111111111111111111111111111111111111111111111111111111111111111111111111111111111111111111111111111111111111111111111 ,
b11111111111111111111111111111111111111111111111111111111111111111111111111111111111111111111111111111111111111111111111111111111 .
b1000001011011000110110000100000011011110110111001100101011100110010000001110011011101000110000101110100011001010010000001100001011011100110010000100000011010110110010101111001 -
#40000
b100000010000000110000010000000101000001100000011100001000000010010000101000001011000011000000110100001110000011110000 !
b100000010000000110000010000000101000001100000011100001000000010010000101000001011000011000000110100001110000011110000 *
b100000010000000110000010000000101000001100000011100001000000010010000101000001011000011000000110100001110000011110000 +
b10000001000000011000001000000010100000110000001110000100000001001000010100000101100001100000011010000111000001111 "
b10000001000000011000001000000010100000110000001110000100000001001000010100000101100001100000011010000111000001111 (
b100010010001000110011010001000101010101100110011101111000100010011001101010101011101111001100110111011110111011111111 #
b100010010001000110011010001000101010101100110011101111000100010011001101010101011101111001100110111011110111011111111 )
b101 %
b10000001000000011000001000000010100000110000001110000100000001001000010100000101100001100000011010000111000001111 ,
b100010010001000110011010001000101010101100110011101111000100010011001101010101011101111001100110111011110111011111111 .
b100011001001001010100000101001100101101001100010011100100110111001000000100000101110000011100000110010101101110011001000110100101111000001000000100001000100000001011010010000001010010011011110111010101101110011001000010000000110000 -
#50000
b11011101101011010101101111100011011001000001001101110011011101110101100100001011111101111010001100101101001001010110000001000110 !
b11011101101011010101101111100011011001000001001101110011011101110101100100001011111101111010001100101101001001010110000001000110 *
b11011101101011010101101111100011011001000001001101110011011101110101100100001011111101111010001100101101001001010110000001000110 +
b101011011000010101000111001100100100011001100101010001100011100101100101100010101001000100011100001111111101111101000001010 "
b101011011000010101000111001100100100011001100101010001100011100101100101100010101001000100011100001111111101111101000001010 (
b11011000110000010111000111011010111101100010000001011001010001101001001000100111101000110010101111001100110110111001101001001100 #
b11011000110000010111000111011010111101100010000001011001010001101001001000100111101000110010101111001100110110111001101001001100 )
b110 %
b101011011000010101000111001100100100011001100101010001100011100101100101100010101001000100011100001111111101111101000001010 ,
b11011000110000010111000111011010111101100010000001011001010001101001001000100111101000110010101111001100110110111001101001001100 .
b100011001001001010100000101001100101101001100010011100100110111001000000100001100101110001100110010000001010010011011110111010101101110011001000010000000110001 -
#60000
b1110000011000000111000001000000011100000110000001110000000000000111000001100000011100000100000001110000011000000111000010000 !
b1110000011000000111000001000000011100000110000001110000000000000111000001100000011100000100000001110000011000000111000010000 *
b1000000100000001100000100000001010000011000000111000010000000100100001010000010110000110000001101000011100000111100010000 "
b1000000100000001100000100000001010000011000000111000010000000100100001010000010110000110000001101000011100000111100010000 (
b1111000011100000110100001100000010110000101000001001000010000000011100000110000001010000010000000011000000100000000100000000 #
b1111000011100000110100001100000010110000101000001001000010000000011100000110000001010000010000000011000000100000000100000000 )
b111 %
b1000000100000001100000100000001010000011000000111000010000000100100001010000010110000110000001101000011100000111100010000 3
b1111000011100000110100001100000010110000101000001001000010000000011100000110000001010000010000000011000000100000000100000000 2
b10010010110010001100101011011100111010001101001011101000111100100100000001011010010000001010011011001010111000101110101011001010110111001110100011010010110000101101100001000000111001101110100011000010111010001100101 4
#70000
b1111000011100000110100001100000010110000101000001001000010000000011100000110000001010000010000000011000000100000000100000000 !
b1111000011100000110100001100000010110000101000001001000010000000011100000110000001010000010000000011000000100000000100000000 *
b1110000011000000111000001000000011100000110000001110000000000000111000001100000011100000100000001110000011000000111000010000 #
b1110000011000000111000001000000011100000110000001110000000000000111000001100000011100000100000001110000011000000111000010000 )
b1110000011000000111000001000000011100000110000001110000000000000111000001100000011100000100000001110000011000000111000010000 0
#80000
b100000010000000110000010000000101000001100000011100001000000010010000101000001011000011000000110100001110000011110000 !
b100000010000000110000010000000101000001100000011100001000000010010000101000001011000011000000110100001110000011110000 *
b10000001000000011000001000000010100000110000001110000100000001001000010100000101100001100000011010000111000001111 "
b10000001000000011000001000000010100000110000001110000100000001001000010100000101100001100000011010000111000001111 (
b100010010001000110011010001000101010101100110011101111000100010011001101010101011101111001100110111011110111011111111 #
b100010010001000110011010001000101010101100110011101111000100010011001101010101011101111001100110111011110111011111111 )
b1000 %
b10000001000000011000001000000010100000110000001110000100000001001000010100000101100001100000011010000111000001111 3
b100010010001000110011010001000101010101100110011101111000100010011001101010101011101111001100110111011110111011111111 2
b1001001011001000110010101101110011101000110100101110100011110010010000000101101001000000100011001001001010100000101001100101101001100010011100100110111001000000111001101110100011000010111010001100101 4
b1111000011100000110100001100000010110000101000001001000010000000011100000110000001010000010000000011000000100000000100000000 1
#90000
b100010010001000110011010001000101010101100110011101111000100010011001101010101011101111001100110111011110111011111111 !
b100010010001000110011010001000101010101100110011101111000100010011001101010101011101111001100110111011110111011111111 *
b100000010000000110000010000000101000001100000011100001000000010010000101000001011000011000000110100001110000011110000 #
b100000010000000110000010000000101000001100000011100001000000010010000101000001011000011000000110100001110000011110000 )
b100000010000000110000010000000101000001100000011100001000000010010000101000001011000011000000110100001110000011110000 0
#100000
b1110001011100011101110000001010001011111010001011111010001010010000110101001010001111010001101000101110100101011010010011000000 !
b1110001011100011101110000001010001011111010001011111010001010010000110101001010001111010001101000101110100101011010010011000000 *
b11111111111011101101110111001100101110111010101010011001100010000111011101100110010101010100010000110011001000100001000100000000 "
b11111111111011101101110111001100101110111010101010011001100010000111011101100110010101010100010000110011001000100001000100000000 (
b10001110100111110000000111000110100101000000100001100011101000010111101000101100011010000101111000011101101101111011010111000000 #
b10001110100111110000000111000110100101000000100001100011101000010111101000101100011010000101111000011101101101111011010111000000 )
b1001 %
b11111111111011101101110111001100101110111010101010011001100010000111011101100110010101010100010000110011001000100001000100000000 3
b10001110100111110000000111000110100101000000100001100011101000010111101000101100011010000101111000011101101101111011010111000000 2
b1001001011001000110010101101110011101000110100101110100011110010010000000101101001000000101001001100001011011100110010001101111011011010010000000110001 4
b100010010001000110011010001000101010101100110011101111000100010011001101010101011101111001100110111011110111011111111 1
#110000
b10001110100111110000000111000110100101000000100001100011101000010111101000101100011010000101111000011101101101111011010111000000 !
b10001110100111110000000111000110100101000000100001100011101000010111101000101100011010000101111000011101101101111011010111000000 *
b1110001011100011101110000001010001011111010001011111010001010010000110101001010001111010001101000101110100101011010010011000000 #
b1110001011100011101110000001010001011111010001011111010001010010000110101001010001111010001101000101110100101011010010011000000 )
b1110001011100011101110000001010001011111010001011111010001010010000110101001010001111010001101000101110100101011010010011000000 0
#120000
b1010101010101010101010101010101101010101010101010101010101010100101010101010101010101010101010110101010101010101010101010101010 !
b1010101010101010101010101010101101010101010101010101010101010100101010101010101010101010101010110101010101010101010101010101010 *
b10101010101010101010101010101010010101010101010101010101010101011010101010101010101010101010101001010101010101010101010101010101 "
b10101010101010101010101010101010010101010101010101010101010101011010101010101010101010101010101001010101010101010101010101010101 (
b11111111111111111111111111111111111111111111111111111111111111111111111111111111111111111111111111111111111111111111111111111111 #
b11111111111111111111111111111111111111111111111111111111111111111111111111111111111111111111111111111111111111111111111111111111 )
b1010 %
b10101010101010101010101010101010010101010101010101010101010101011010101010101010101010101010101001010101010101010101010101010101 3
b11111111111111111111111111111111111111111111111111111111111111111111111111111111111111111111111111111111111111111111111111111111 2
b1001001011001000110010101101110011101000110100101110100011110010010000000101101001000000100000101101100011011000010000000110000011110000100011001000110 4
b10001110100111110000000111000110100101000000100001100011101000010111101000101100011010000101111000011101101101111011010111000000 1
#130000
b11111111111111111111111111111111111111111111111111111111111111111111111111111111111111111111111111111111111111111111111111111111 !
b11111111111111111111111111111111111111111111111111111111111111111111111111111111111111111111111111111111111111111111111111111111 *
b1010101010101010101010101010101101010101010101010101010101010100101010101010101010101010101010110101010101010101010101010101010 #
b1010101010101010101010101010101101010101010101010101010101010100101010101010101010101010101010110101010101010101010101010101010 )
b1010101010101010101010101010101101010101010101010101010101010100101010101010101010101010101010110101010101010101010101010101010 0
#140000
b11111111111111111111111111111111000000000000000000000000000000000000000000000000000000000000000011111111111111111111111111111111 !
b11111111111111111111111111111111000000000000000000000000000000000000000000000000000000000000000011111111111111111111111111111111 *
b1010101010101010101010101010101010101010101010101010101010101011010101010101010101010101010101010101010101010101010101010101010 "
b1010101010101010101010101010101010101010101010101010101010101011010101010101010101010101010101010101010101010101010101010101010 (
b10101010101010101010101010101010010101010101010101010101010101011010101010101010101010101010101001010101010101010101010101010101 #
b10101010101010101010101010101010010101010101010101010101010101011010101010101010101010101010101001010101010101010101010101010101 )
b1011 %
b1010101010101010101010101010101010101010101010101010101010101011010101010101010101010101010101010101010101010101010101010101010 3
b10101010101010101010101010101010010101010101010101010101010101011010101010101010101010101010101001010101010101010101010101010101 2
b1001001011001000110010101101110011101000110100101110100011110010010000000101101001000000100000101101100011101000110010101110010011011100110000101110100011010010110111001100111 4
b11111111111111111111111111111111111111111111111111111111111111111111111111111111111111111111111111111111111111111111111111111111 1
#150000
b10101010101010101010101010101010010101010101010101010101010101011010101010101010101010101010101001010101010101010101010101010101 !
b10101010101010101010101010101010010101010101010101010101010101011010101010101010101010101010101001010101010101010101010101010101 *
b11111111111111111111111111111111000000000000000000000000000000000000000000000000000000000000000011111111111111111111111111111111 #
b11111111111111111111111111111111000000000000000000000000000000000000000000000000000000000000000011111111111111111111111111111111 )
b11111111111111111111111111111111000000000000000000000000000000000000000000000000000000000000000011111111111111111111111111111111 0
#160000
b1 !
b1 *
b1 +
b0 "
b0 (
b1 #
b1 )
b1100 %
b0 ,
b1 .
b10100110110100101101110011001110110110001100101001000000110001001101001011101000010000001101001011011100010000001110011011101000110000101110100011001010010000000101000011000100110100101110100001000000011000000101001 -
b10101010101010101010101010101010010101010101010101010101010101011010101010101010101010101010101001010101010101010101010101010101 1
#170000
b10000000000000000000000000000000000000000000000000000000000000000000000000000000000000000000000000000000000000000000000000000000 !
b10000000000000000000000000000000000000000000000000000000000000000000000000000000000000000000000000000000000000000000000000000000 *
b10000000000000000000000000000000000000000000000000000000000000000000000000000000000000000000000000000000000000000000000000000000 +
b10000000000000000000000000000000000000000000000000000000000000000000000000000000000000000000000000000000000000000000000000000000 #
b10000000000000000000000000000000000000000000000000000000000000000000000000000000000000000000000000000000000000000000000000000000 )
b1101 %
b10000000000000000000000000000000000000000000000000000000000000000000000000000000000000000000000000000000000000000000000000000000 .
b101001101101001011011100110011101101100011001010010000001100010011010010111010000100000011010010110111000100000011100110111010001100001011101000110010100100000001010000110001001101001011101000010000000110001001100100011011100101001 -
#180000
b1 !
b1 *
b1 +
b1 "
b1 (
b0 #
b0 )
b1110 %
b1 ,
b0 .
b1010011011010010110111001100111011011000110010100100000011000100110100101110100001000000110100101101110001000000110101101100101011110010010000000101000011000100110100101110100001000000011000000101001 -
#190000
b10000000000000000000000000000000000000000000000000000000000000000000000000000000000000000000000000000000000000000000000000000000 !
b10000000000000000000000000000000000000000000000000000000000000000000000000000000000000000000000000000000000000000000000000000000 *
b10000000000000000000000000000000000000000000000000000000000000000000000000000000000000000000000000000000000000000000000000000000 +
b10000000000000000000000000000000000000000000000000000000000000000000000000000000000000000000000000000000000000000000000000000000 "
b10000000000000000000000000000000000000000000000000000000000000000000000000000000000000000000000000000000000000000000000000000000 (
b1111 %
b10000000000000000000000000000000000000000000000000000000000000000000000000000000000000000000000000000000000000000000000000000000 ,
b10100110110100101101110011001110110110001100101001000000110001001101001011101000010000001101001011011100010000001101011011001010111100100100000001010000110001001101001011101000010000000110001001100100011011100101001 -
#200000
b11111111111111111111111111111111111111111111111111111111111111111111111111111111111111111111111111111111111111111111111111111111 !
b11111111111111111111111111111111111111111111111111111111111111111111111111111111111111111111111111111111111111111111111111111111 *
b11111111111111111111111111111111111111111111111111111111111111111111111111111111111111111111111111111111111111111111111111111111 +
b0 "
b0 (
b11111111111111111111111111111111111111111111111111111111111111111111111111111111111111111111111111111111111111111111111111111111 #
b11111111111111111111111111111111111111111111111111111111111111111111111111111111111111111111111111111111111111111111111111111111 )
b10000 %
b0 ,
b11111111111111111111111111111111111111111111111111111111111111111111111111111111111111111111111111111111111111111111111111111111 .
b10011010110000101111000001000000111001101110100011000010111010001100101001011000010000001101101011010010110111000100000011010110110010101111001 -
#210000
b11111111111111111111111111111111111111111111111111111111111111111111111111111111111111111111111111111111111111111111111111111111 "
b11111111111111111111111111111111111111111111111111111111111111111111111111111111111111111111111111111111111111111111111111111111 (
b0 #
b0 )
b10001 %
b11111111111111111111111111111111111111111111111111111111111111111111111111111111111111111111111111111111111111111111111111111111 ,
b0 .
b10011010110100101101110001000000111001101110100011000010111010001100101001011000010000001101101011000010111100000100000011010110110010101111001 -
#220000
b0 !
b0 *
b0 +
b1010101010101010101010101010101010101010101010101010101010101010101010101010101010101010101010101010101010101010101010101010101 "
b1010101010101010101010101010101010101010101010101010101010101010101010101010101010101010101010101010101010101010101010101010101 (
b1010101010101010101010101010101010101010101010101010101010101010101010101010101010101010101010101010101010101010101010101010101 #
b1010101010101010101010101010101010101010101010101010101010101010101010101010101010101010101010101010101010101010101010101010101 )
b10010 %
b1010101010101010101010101010101010101010101010101010101010101010101010101010101010101010101010101010101010101010101010101010101 ,
b1010101010101010101010101010101010101010101010101010101010101010101010101010101010101010101010101010101010101010101010101010101 .
b1000001011011000111010001100101011100100110111001100001011101000110100101101110011001110010000000110000011110000011010100110101 -
#230000
b10101010101010101010101010101010101010101010101010101010101010101010101010101010101010101010101010101010101010101010101010101010 "
b10101010101010101010101010101010101010101010101010101010101010101010101010101010101010101010101010101010101010101010101010101010 (
b10101010101010101010101010101010101010101010101010101010101010101010101010101010101010101010101010101010101010101010101010101010 #
b10101010101010101010101010101010101010101010101010101010101010101010101010101010101010101010101010101010101010101010101010101010 )
b10011 %
b10101010101010101010101010101010101010101010101010101010101010101010101010101010101010101010101010101010101010101010101010101010 ,
b10101010101010101010101010101010101010101010101010101010101010101010101010101010101010101010101010101010101010101010101010101010 .
b1000001011011000111010001100101011100100110111001100001011101000110100101101110011001110010000000110000011110000100000101000001 -
#240000
b10000000001101100101001010101010101011000011110000111001000000110001101100110111011100001011011011101111001111100001111111001101 !
b10000000001101100101001010101010101011000011110000111001000000110001101100110111011100001011011011101111001111100001111111001101 *
b10000000001101100101001010101010101011000011110000111001000000110001101100110111011100001011011011101111001111100001111111001101 +
b10100100000010010011100000100010001010011001111100110001110100000000100000101110111110101001100011101100010011100110110010001001 "
b10100100000010010011100000100010001010011001111100110001110100000000100000101110111110101001100011101100010011100110110010001001 (
b100100001111110110101010001000100001011010001100001000110100110001001100011001100010100010111000000011011100000111001101000100 #
b100100001111110110101010001000100001011010001100001000110100110001001100011001100010100010111000000011011100000111001101000100 )
b10100 %
b10100100000010010011100000100010001010011001111100110001110100000000100000101110111110101001100011101100010011100110110010001001 ,
b100100001111110110101010001000100001011010001100001000110100110001001100011001100010100010111000000011011100000111001101000100 .
b101001001100001011011100110010001101111011011010010000000110001 -
#250000
b10000101100001000000100001010001111100011010110001000011101010101000000111010000101100110111101010000001101011100000010101111011 !
b10000101100001000000100001010001111100011010110001000011101010101000000111010000101100110111101010000001101011100000010101111011 *
b10000101100001000000100001010001111100011010110001000011101010101000000111010000101100110111101010000001101011100000010101111011 +
b11000000101011000010100110110111110010010111110001010000110111010011111110000100110101011011010110110101010001110000100100010111 "
b11000000101011000010100110110111110010010111110001010000110111010011111110000100110101011011010110110101010001110000100100010111 (
b1000101001010000010000111100110001110001101000000010011011101111011111001010100011001101100111100110100111010010000110001101100 #
b1000101001010000010000111100110001110001101000000010011011101111011111001010100011001101100111100110100111010010000110001101100 )
b10101 %
b11000000101011000010100110110111110010010111110001010000110111010011111110000100110101011011010110110101010001110000100100010111 ,
b1000101001010000010000111100110001110001101000000010011011101111011111001010100011001101100111100110100111010010000110001101100 .
b101001001100001011011100110010001101111011011010010000000110010 -
#260000
b100100011000110000111011100011010000010101001101001010101100111100110110011010101011011101100000000000011001110011000011011111 !
b100100011000110000111011100011010000010101001101001010101100111100110110011010101011011101100000000000011001110011000011011111 *
b100100011000110000111011100011010000010101001101001010101100111100110110011010101011011101100000000000011001110011000011011111 +
b11111010110011101011000000001100100010111010110111110000000011011101111010101101101111101110111111011110110010101111000000000001 "
b11111010110011101011000000001100100010111010110111110000000011011101111010101101101111101110111111011110110010101111000000000001 (
b11011110101011011011111011101111110010101111111010111010101111100001001100110111000100110011011111011110101011011100000011011110 #
b11011110101011011011111011101111110010101111111010111010101111100001001100110111000100110011011111011110101011011100000011011110 )
b10110 %
b11111010110011101011000000001100100010111010110111110000000011011101111010101101101111101110111111011110110010101111000000000001 ,
b11011110101011011011111011101111110010101111111010111010101111100001001100110111000100110011011111011110101011011100000011011110 .
b101001001100001011011100110010001101111011011010010000000110011 -
