RTL/gf_mult.v
// ============================================================================
// Galois Field GF(2^8) Multiplication Module
// Target: Tang Mega 60K (GOWIN GW5AT-LV60PG484AC1)
// Description: Nhân trong trường Galois GF(2^8) cho MixColumns
// Polynomial: 0x11B (x^8 + x^4 + x^3 + x + 1)
// ============================================================================

module gf_mult (
    input  wire [7:0] a,      // Toán hạng thứ nhất
    input  wire [7:0] b,      // Toán hạng thứ hai (thường là hằng số 0x02, 0x03, 0x09, 0x0b, 0x0d, 0x0e)
    output wire [7:0] product // Kết quả nhân trong GF(2^8)
);

// ============================================================================
// Nhân với 0x02 (x) trong GF(2^8)
// ============================================================================
function [7:0] gf_mult_by_02;
    input [7:0] in;
    begin
        // Nếu bit cao = 1, shift left và XOR với 0x1b
        // Nếu bit cao = 0, chỉ shift left
        gf_mult_by_02 = (in[7] == 1'b1) ? ((in << 1) ^ 8'h1b) : (in << 1);
    end
endfunction

// ============================================================================
// Nhân với 0x03 (x + 1) trong GF(2^8)
// ============================================================================
function [7:0] gf_mult_by_03;
    input [7:0] in;
    begin
        // 0x03 * in = (0x02 * in) XOR in
        gf_mult_by_03 = gf_mult_by_02(in) ^ in;
    end
endfunction

// ============================================================================
// Nhân với 0x09 (x^3 + 1) trong GF(2^8)
// ============================================================================
function [7:0] gf_mult_by_09;
    input [7:0] in;
    reg [7:0] temp;
    begin
        temp = gf_mult_by_02(in);           // x
        temp = gf_mult_by_02(temp);         // x^2
        temp = gf_mult_by_02(temp);         // x^3
        gf_mult_by_09 = temp ^ in;          // x^3 + 1
    end
endfunction

// ============================================================================
// Nhân với 0x0b (x^3 + x + 1) trong GF(2^8)
// ============================================================================
function [7:0] gf_mult_by_0b;
    input [7:0] in;
    reg [7:0] temp;
    begin
        temp = gf_mult_by_02(in);           // x
        temp = gf_mult_by_02(temp) ^ in;    // x^2 + 1
        temp = gf_mult_by_02(temp) ^ in;    // x^3 + x + 1
        gf_mult_by_0b = temp;
    end
endfunction

// ============================================================================
// Nhân với 0x0d (x^3 + x^2 + 1) trong GF(2^8)
// ============================================================================
function [7:0] gf_mult_by_0d;
    input [7:0] in;
    reg [7:0] x2, x4, x8;
    begin
        x2 = gf_mult_by_02(in);             // x^2
        x4 = gf_mult_by_02(x2);             // x^4
        x8 = gf_mult_by_02(x4);             // x^8
        gf_mult_by_0d = x8 ^ x4 ^ in;       // x^8 XOR x^4 XOR 1 = 0x0D
    end
endfunction

// ============================================================================
// Nhân với 0x0e (x^3 + x^2 + x) trong GF(2^8)
// ============================================================================
function [7:0] gf_mult_by_0e;
    input [7:0] in;
    reg [7:0] x2, x4, x8;
    begin
        x2 = gf_mult_by_02(in);             // x^2
        x4 = gf_mult_by_02(x2);             // x^4
        x8 = gf_mult_by_02(x4);             // x^8
        gf_mult_by_0e = x8 ^ x4 ^ x2;       // x^8 XOR x^4 XOR x^2 = 0x0E
    end
endfunction

// ============================================================================
// Multiplexer - Chọn phép nhân dựa trên giá trị b
// ============================================================================
assign product = (b == 8'h01) ? a :
                 (b == 8'h02) ? gf_mult_by_02(a) :
                 (b == 8'h03) ? gf_mult_by_03(a) :
                 (b == 8'h09) ? gf_mult_by_09(a) :
                 (b == 8'h0b) ? gf_mult_by_0b(a) :
                 (b == 8'h0d) ? gf_mult_by_0d(a) :
                 (b == 8'h0e) ? gf_mult_by_0e(a) :
                 8'h00; // Default

endmodule

tb_aes256/tb_gf_mult.v
// ============================================================================
// Testbench for Galois Field GF(2^8) Multiplication Module
// Target: Simulation with GTKWave
// Description: Kiểm tra tất cả các phép nhân GF(2^8) với test vectors
// ============================================================================

`timescale 1ns / 1ps

module tb_gf_mult;

// ============================================================================
// Signals
// ============================================================================
reg  [7:0] a;
reg  [7:0] b;
wire [7:0] product;

integer i;
integer errors;

// ============================================================================
// DUT Instantiation
// ============================================================================
gf_mult uut (
    .a(a),
    .b(b),
    .product(product)
);

// ============================================================================
// Test Vectors - FIPS-197 và test cases đã verify
// ============================================================================
initial begin
    // Khởi tạo
    errors = 0;
    a = 8'h00;
    b = 8'h00;
    
    // Dump waveforms cho GTKWave
    $dumpfile("tb_gf_mult.vcd");
    $dumpvars(0, tb_gf_mult);
    
    $display("========================================");
    $display("GF(2^8) Multiplication Testbench");
    $display("========================================");
    
    // ========================================================================
    // Test 1: Nhân với 0x00 (kết quả luôn là 0x00)
    // ========================================================================
    $display("\n[Test 1] Multiplication by 0x00");
    #10;
    a = 8'h00; b = 8'h02; #10;
    check_result(8'h00, "0x00 * 0x02");
    
    a = 8'h57; b = 8'h00; #10;
    // Note: b=0x00 không được support trong module, sẽ trả về 0x00 (default)
    if (product == 8'h00)
        $display("  PASS: 0x57 * 0x00 = 0x%02h", product);
    else begin
        $display("  FAIL: 0x57 * 0x00 = 0x%02h (expected 0x00)", product);
        errors = errors + 1;
    end
    
    // ========================================================================
    // Test 2: Nhân với 0x01 (identity - kết quả = a)
    // ========================================================================
    $display("\n[Test 2] Multiplication by 0x01 (Identity)");
    #10;
    a = 8'h00; b = 8'h01; #10; check_result(8'h00, "0x00 * 0x01");
    a = 8'h01; b = 8'h01; #10; check_result(8'h01, "0x01 * 0x01");
    a = 8'h57; b = 8'h01; #10; check_result(8'h57, "0x57 * 0x01");
    a = 8'hFF; b = 8'h01; #10; check_result(8'hFF, "0xFF * 0x01");
    
    // ========================================================================
    // Test 3: Nhân với 0x02 (xtime operation)
    // ========================================================================
    $display("\n[Test 3] Multiplication by 0x02");
    #10;
    a = 8'h00; b = 8'h02; #10; check_result(8'h00, "0x00 * 0x02");
    a = 8'h01; b = 8'h02; #10; check_result(8'h02, "0x01 * 0x02");
    a = 8'h02; b = 8'h02; #10; check_result(8'h04, "0x02 * 0x02");
    a = 8'h57; b = 8'h02; #10; check_result(8'hAE, "0x57 * 0x02");
    a = 8'h83; b = 8'h02; #10; check_result(8'h1D, "0x83 * 0x02"); // bit[7]=1, cần XOR 0x1B
    a = 8'hCA; b = 8'h02; #10; check_result(8'h8F, "0xCA * 0x02");
    a = 8'hFF; b = 8'h02; #10; check_result(8'hE5, "0xFF * 0x02");
    
    // ========================================================================
    // Test 4: Nhân với 0x03
    // ========================================================================
    $display("\n[Test 4] Multiplication by 0x03");
    #10;
    a = 8'h00; b = 8'h03; #10; check_result(8'h00, "0x00 * 0x03");
    a = 8'h01; b = 8'h03; #10; check_result(8'h03, "0x01 * 0x03");
    a = 8'h02; b = 8'h03; #10; check_result(8'h06, "0x02 * 0x03");
    a = 8'h57; b = 8'h03; #10; check_result(8'hF9, "0x57 * 0x03"); // 0xAE XOR 0x57
    a = 8'h83; b = 8'h03; #10; check_result(8'h9E, "0x83 * 0x03");
    a = 8'hCA; b = 8'h03; #10; check_result(8'h45, "0xCA * 0x03");
    a = 8'hFF; b = 8'h03; #10; check_result(8'h1A, "0xFF * 0x03");
    
    // ========================================================================
    // Test 5: Nhân với 0x09 (cho InvMixColumns)
    // ========================================================================
    $display("\n[Test 5] Multiplication by 0x09");
    #10;
    a = 8'h00; b = 8'h09; #10; check_result(8'h00, "0x00 * 0x09");
    a = 8'h01; b = 8'h09; #10; check_result(8'h09, "0x01 * 0x09");
    a = 8'h02; b = 8'h09; #10; check_result(8'h12, "0x02 * 0x09");
    a = 8'h57; b = 8'h09; #10; check_result(8'hD9, "0x57 * 0x09");
    a = 8'h83; b = 8'h09; #10; check_result(8'hF7, "0x83 * 0x09");
    a = 8'hCA; b = 8'h09; #10; check_result(8'hC0, "0xCA * 0x09");
    a = 8'hFF; b = 8'h09; #10; check_result(8'h46, "0xFF * 0x09");
    
    // ========================================================================
    // Test 6: Nhân với 0x0B (cho InvMixColumns)
    // ========================================================================
    $display("\n[Test 6] Multiplication by 0x0B");
    #10;
    a = 8'h00; b = 8'h0B; #10; check_result(8'h00, "0x00 * 0x0B");
    a = 8'h01; b = 8'h0B; #10; check_result(8'h0B, "0x01 * 0x0B");
    a = 8'h02; b = 8'h0B; #10; check_result(8'h16, "0x02 * 0x0B");
    a = 8'h57; b = 8'h0B; #10; check_result(8'h77, "0x57 * 0x0B");
    a = 8'h83; b = 8'h0B; #10; check_result(8'hEA, "0x83 * 0x0B");
    a = 8'hCA; b = 8'h0B; #10; check_result(8'h4F, "0xCA * 0x0B");
    a = 8'hFF; b = 8'h0B; #10; check_result(8'hA3, "0xFF * 0x0B");
    
    // ========================================================================
    // Test 7: Nhân với 0x0D (cho InvMixColumns)
    // ========================================================================
    $display("\n[Test 7] Multiplication by 0x0D");
    #10;
    a = 8'h00; b = 8'h0D; #10; check_result(8'h00, "0x00 * 0x0D");
    a = 8'h01; b = 8'h0D; #10; check_result(8'h0D, "0x01 * 0x0D");
    a = 8'h02; b = 8'h0D; #10; check_result(8'h1A, "0x02 * 0x0D");
    a = 8'h57; b = 8'h0D; #10; check_result(8'h9E, "0x57 * 0x0D");
    a = 8'h83; b = 8'h0D; #10; check_result(8'hCD, "0x83 * 0x0D");
    a = 8'hCA; b = 8'h0D; #10; check_result(8'hC5, "0xCA * 0x0D");
    a = 8'hFF; b = 8'h0D; #10; check_result(8'h97, "0xFF * 0x0D");
    
    // ========================================================================
    // Test 8: Nhân với 0x0E (cho InvMixColumns)
    // ========================================================================
    $display("\n[Test 8] Multiplication by 0x0E");
    #10;
    a = 8'h00; b = 8'h0E; #10; check_result(8'h00, "0x00 * 0x0E");
    a = 8'h01; b = 8'h0E; #10; check_result(8'h0E, "0x01 * 0x0E");
    a = 8'h02; b = 8'h0E; #10; check_result(8'h1C, "0x02 * 0x0E");
    a = 8'h57; b = 8'h0E; #10; check_result(8'h67, "0x57 * 0x0E");
    a = 8'h83; b = 8'h0E; #10; check_result(8'h53, "0x83 * 0x0E");
    a = 8'hCA; b = 8'h0E; #10; check_result(8'h80, "0xCA * 0x0E");
    a = 8'hFF; b = 8'h0E; #10; check_result(8'h8D, "0xFF * 0x0E");
    
    // ========================================================================
    // Test 9: FIPS-197 MixColumns Example
    // ========================================================================
    $display("\n[Test 9] FIPS-197 MixColumns Example");
    $display("Input column: [D4, BF, 5D, 30]");
    #10;
    
    // First byte of result: 0x04
    // 0x02*D4 XOR 0x03*BF XOR 0x01*5D XOR 0x01*30
    a = 8'hD4; b = 8'h02; #10;
    $display("  0x02 * 0xD4 = 0x%02h", product);
    a = 8'hBF; b = 8'h03; #10;
    $display("  0x03 * 0xBF = 0x%02h", product);
    $display("  Result: 0xB3 XOR 0x7C XOR 0x5D XOR 0x30 = 0x04");
    
    // ========================================================================
    // Test 10: Kiểm tra các edge cases
    // ========================================================================
    $display("\n[Test 10] Edge Cases");
    #10;
    
    // Nhân hai số lớn
    a = 8'hFF; b = 8'h0D; #10;
    check_result(8'h97, "0xFF * 0x0D");
    
    a = 8'hFF; b = 8'h0E; #10;
    check_result(8'h8D, "0xFF * 0x0E");
    
    // Giá trị b không hợp lệ (không được support)
    a = 8'h57; b = 8'h07; #10;
    if (product == 8'h00)
        $display("  PASS: 0x57 * 0x07 = 0x00 (unsupported, returns default)");
    else begin
        $display("  FAIL: Unsupported b value should return 0x00, got 0x%02h", product);
        errors = errors + 1;
    end
    
    // ========================================================================
    // Final Summary
    // ========================================================================
    #10;
    $display("\n========================================");
    $display("Test Summary:");
    $display("========================================");
    if (errors == 0) begin
        $display("ALL TESTS PASSED!");
        $display("GF(2^8) multiplication module is CORRECT!");
    end else begin
        $display("TESTS FAILED: %0d errors found", errors);
        $display("GF(2^8) multiplication module has BUGS!");
    end
    $display("========================================\n");
    
    // Kết thúc simulation
    #100;
    $finish;
end

// ============================================================================
// Task để kiểm tra kết quả
// ============================================================================
task check_result;
    input [7:0] expected;
    input [80*8:1] test_name;
    begin
        if (product == expected) begin
            $display("  PASS: %0s = 0x%02h", test_name, product);
        end else begin
            $display("  FAIL: %0s = 0x%02h (expected 0x%02h)", test_name, product, expected);
            errors = errors + 1;
        end
    end
endtask

// ============================================================================
// Monitor - Hiển thị mọi thay đổi
// ============================================================================
initial begin
    $monitor("Time=%0t a=0x%02h b=0x%02h product=0x%02h", 
             $time, a, b, product);
end

endmodule

gtkwave/tb_gf_mult.vcd
$date
	Mon Nov  3 15:33:57 2025
$end
$version
	Icarus Verilog
$end
$timescale
	1ps
$end
$scope module tb_gf_mult $end
$var wire 8 ! product [7:0] $end
$var reg 8 " a [7:0] $end
$var reg 8 # b [7:0] $end
$var integer 32 $ errors [31:0] $end
$scope module uut $end
$var wire 8 % a [7:0] $end
$var wire 8 & b [7:0] $end
$var wire 8 ' product [7:0] $end
$scope function gf_mult_by_02 $end
$var reg 8 ( in [7:0] $end
$upscope $end
$scope function gf_mult_by_03 $end
$var reg 8 ) in [7:0] $end
$upscope $end
$scope function gf_mult_by_09 $end
$var reg 8 * in [7:0] $end
$var reg 8 + temp [7:0] $end
$upscope $end
$scope function gf_mult_by_0b $end
$var reg 8 , in [7:0] $end
$var reg 8 - temp [7:0] $end
$upscope $end
$scope function gf_mult_by_0d $end
$var reg 8 . in [7:0] $end
$var reg 8 / x2 [7:0] $end
$var reg 8 0 x4 [7:0] $end
$var reg 8 1 x8 [7:0] $end
$upscope $end
$scope function gf_mult_by_0e $end
$var reg 8 2 in [7:0] $end
$var reg 8 3 x2 [7:0] $end
$var reg 8 4 x4 [7:0] $end
$var reg 8 5 x8 [7:0] $end
$upscope $end
$upscope $end
$scope task check_result $end
$var reg 8 6 expected [7:0] $end
$var reg 640 7 test_name [640:1] $end
$upscope $end
$upscope $end
$enddefinitions $end
$comment Show the parameter values. $end
$dumpall
$end
#0
$dumpvars
bx 7
bx 6
b0 5
b0 4
b0 3
b0 2
b0 1
b0 0
b0 /
b0 .
b0 -
b0 ,
b0 +
b0 *
b0 )
b0 (
b0 '
b0 &
b0 %
b0 $
b0 #
b0 "
b0 !
$end
#10000
b10 #
b10 &
#20000
b1010111 )
b10001110 +
b1010111 *
b1110111 -
b1010111 ,
b10001110 1
b1000111 0
b10101110 /
b1010111 .
b10001110 5
b1000111 4
b10101110 3
b1010111 (
b1010111 2
b0 #
b0 &
b1010111 "
b1010111 %
b11000001111000001100000011000000100000001010100010000000110000011110000011000000110010 7
b0 6
#40000
b0 )
b0 +
b0 *
b0 -
b0 ,
b0 1
b0 0
b0 /
b0 .
b0 5
b0 4
b0 3
b0 (
b0 2
b1 #
b1 &
b0 "
b0 %
#50000
b1 )
b1000 +
b1 *
b1011 -
b1 ,
b1000 1
b100 0
b10 /
b1 .
b1000 5
b100 4
b10 3
b1 (
b1 2
b1 !
b1 '
b1 "
b1 %
b11000001111000001100000011000000100000001010100010000000110000011110000011000000110001 7
#60000
b1010111 )
b10001110 +
b1010111 *
b1110111 -
b1010111 ,
b10001110 1
b1000111 0
b10101110 /
b1010111 .
b10001110 5
b1000111 4
b10101110 3
b1010111 (
b1010111 2
b1010111 !
b1010111 '
b1010111 "
b1010111 %
b11000001111000001100000011000100100000001010100010000000110000011110000011000000110001 7
b1 6
#70000
b11111111 )
b10111001 +
b11111111 *
b10100011 -
b11111111 ,
b10111001 1
b11010001 0
b11100101 /
b11111111 .
b10111001 5
b11010001 4
b11100101 3
b11111111 (
b11111111 2
b11111111 !
b11111111 '
b11111111 "
b11111111 %
b11000001111000001101010011011100100000001010100010000000110000011110000011000000110001 7
b1010111 6
#80000
b11000001111000010001100100011000100000001010100010000000110000011110000011000000110001 7
b11111111 6
#90000
b0 )
b0 +
b0 *
b0 -
b0 ,
b0 1
b0 0
b0 /
b0 .
b0 5
b0 4
b0 3
b0 (
b0 2
b0 !
b0 '
b10 #
b10 &
b0 "
b0 %
#100000
b10 !
b10 '
b1 )
b1000 +
b1 *
b1011 -
b1 ,
b1000 1
b100 0
b10 /
b1 .
b1000 5
b100 4
b10 3
b1 (
b1 2
b1 "
b1 %
b11000001111000001100000011000000100000001010100010000000110000011110000011000000110010 7
b0 6
#110000
b100 !
b100 '
b10 )
b10000 +
b10 *
b10110 -
b10 ,
b10000 1
b1000 0
b100 /
b10 .
b10000 5
b1000 4
b100 3
b10 (
b10 2
b10 "
b10 %
b11000001111000001100000011000100100000001010100010000000110000011110000011000000110010 7
b10 6
#120000
b10101110 !
b10101110 '
b1010111 )
b10001110 +
b1010111 *
b1110111 -
b1010111 ,
b10001110 1
b1000111 0
b10101110 /
b1010111 .
b10001110 5
b1000111 4
b10101110 3
b1010111 (
b1010111 2
b1010111 "
b1010111 %
b11000001111000001100000011001000100000001010100010000000110000011110000011000000110010 7
b100 6
#130000
b11101 !
b11101 '
b10000011 )
b1110100 +
b10000011 *
b11101010 -
b10000011 ,
b1110100 1
b111010 0
b11101 /
b10000011 .
b1110100 5
b111010 4
b11101 3
b10000011 (
b10000011 2
b10000011 "
b10000011 %
b11000001111000001101010011011100100000001010100010000000110000011110000011000000110010 7
b10101110 6
#140000
b10001111 !
b10001111 '
b11001010 )
b1010 +
b11001010 *
b1001111 -
b11001010 ,
b1010 1
b101 0
b10001111 /
b11001010 .
b1010 5
b101 4
b10001111 3
b11001010 (
b11001010 2
b11001010 "
b11001010 %
b11000001111000001110000011001100100000001010100010000000110000011110000011000000110010 7
b11101 6
#150000
b11100101 !
b11100101 '
b11111111 )
b10111001 +
b11111111 *
b10100011 -
b11111111 ,
b10111001 1
b11010001 0
b11100101 /
b11111111 .
b10111001 5
b11010001 4
b11100101 3
b11111111 (
b11111111 2
b11111111 "
b11111111 %
b11000001111000010000110100000100100000001010100010000000110000011110000011000000110010 7
b10001111 6
#160000
b11000001111000010001100100011000100000001010100010000000110000011110000011000000110010 7
b11100101 6
#170000
b0 !
b0 '
b0 )
b0 +
b0 *
b0 -
b0 ,
b0 1
b0 0
b0 /
b0 .
b0 5
b0 4
b0 3
b0 (
b0 2
b11 #
b11 &
b0 "
b0 %
#180000
b11 !
b11 '
b1 )
b1000 +
b1 *
b1011 -
b1 ,
b1000 1
b100 0
b10 /
b1 .
b1000 5
b100 4
b10 3
b1 (
b1 2
b1 "
b1 %
b11000001111000001100000011000000100000001010100010000000110000011110000011000000110011 7
b0 6
#190000
b110 !
b110 '
b10 )
b10000 +
b10 *
b10110 -
b10 ,
b10000 1
b1000 0
b100 /
b10 .
b10000 5
b1000 4
b100 3
b10 (
b10 2
b10 "
b10 %
b11000001111000001100000011000100100000001010100010000000110000011110000011000000110011 7
b11 6
#200000
b11111001 !
b11111001 '
b1010111 )
b10001110 +
b1010111 *
b1110111 -
b1010111 ,
b10001110 1
b1000111 0
b10101110 /
b1010111 .
b10001110 5
b1000111 4
b10101110 3
b1010111 (
b1010111 2
b1010111 "
b1010111 %
b11000001111000001100000011001000100000001010100010000000110000011110000011000000110011 7
b110 6
#210000
b10011110 !
b10011110 '
b10000011 )
b1110100 +
b10000011 *
b11101010 -
b10000011 ,
b1110100 1
b111010 0
b11101 /
b10000011 .
b1110100 5
b111010 4
b11101 3
b10000011 (
b10000011 2
b10000011 "
b10000011 %
b11000001111000001101010011011100100000001010100010000000110000011110000011000000110011 7
b11111001 6
#220000
b1000101 !
b1000101 '
b11001010 )
b1010 +
b11001010 *
b1001111 -
b11001010 ,
b1010 1
b101 0
b10001111 /
b11001010 .
b1010 5
b101 4
b10001111 3
b11001010 (
b11001010 2
b11001010 "
b11001010 %
b11000001111000001110000011001100100000001010100010000000110000011110000011000000110011 7
b10011110 6
#230000
b11010 !
b11010 '
b11111111 )
b10111001 +
b11111111 *
b10100011 -
b11111111 ,
b10111001 1
b11010001 0
b11100101 /
b11111111 .
b10111001 5
b11010001 4
b11100101 3
b11111111 (
b11111111 2
b11111111 "
b11111111 %
b11000001111000010000110100000100100000001010100010000000110000011110000011000000110011 7
b1000101 6
#240000
b11000001111000010001100100011000100000001010100010000000110000011110000011000000110011 7
b11010 6
#250000
b0 !
b0 '
b0 )
b0 +
b0 *
b0 -
b0 ,
b0 1
b0 0
b0 /
b0 .
b0 5
b0 4
b0 3
b0 (
b0 2
b1001 #
b1001 &
b0 "
b0 %
#260000
b1001 !
b1001 '
b1 )
b1000 +
b1 *
b1011 -
b1 ,
b1000 1
b100 0
b10 /
b1 .
b1000 5
b100 4
b10 3
b1 (
b1 2
b1 "
b1 %
b11000001111000001100000011000000100000001010100010000000110000011110000011000000111001 7
b0 6
#270000
b10010 !
b10010 '
b10 )
b10000 +
b10 *
b10110 -
b10 ,
b10000 1
b1000 0
b100 /
b10 .
b10000 5
b1000 4
b100 3
b10 (
b10 2
b10 "
b10 %
b11000001111000001100000011000100100000001010100010000000110000011110000011000000111001 7
b1001 6
#280000
b11011001 !
b11011001 '
b1010111 )
b10001110 +
b1010111 *
b1110111 -
b1010111 ,
b10001110 1
b1000111 0
b10101110 /
b1010111 .
b10001110 5
b1000111 4
b10101110 3
b1010111 (
b1010111 2
b1010111 "
b1010111 %
b11000001111000001100000011001000100000001010100010000000110000011110000011000000111001 7
b10010 6
#290000
b11110111 !
b11110111 '
b10000011 )
b1110100 +
b10000011 *
b11101010 -
b10000011 ,
b1110100 1
b111010 0
b11101 /
b10000011 .
b1110100 5
b111010 4
b11101 3
b10000011 (
b10000011 2
b10000011 "
b10000011 %
b11000001111000001101010011011100100000001010100010000000110000011110000011000000111001 7
b11011001 6
#300000
b11000000 !
b11000000 '
b11001010 )
b1010 +
b11001010 *
b1001111 -
b11001010 ,
b1010 1
b101 0
b10001111 /
b11001010 .
b1010 5
b101 4
b10001111 3
b11001010 (
b11001010 2
b11001010 "
b11001010 %
b11000001111000001110000011001100100000001010100010000000110000011110000011000000111001 7
b11110111 6
#310000
b1000110 !
b1000110 '
b11111111 )
b10111001 +
b11111111 *
b10100011 -
b11111111 ,
b10111001 1
b11010001 0
b11100101 /
b11111111 .
b10111001 5
b11010001 4
b11100101 3
b11111111 (
b11111111 2
b11111111 "
b11111111 %
b11000001111000010000110100000100100000001010100010000000110000011110000011000000111001 7
b11000000 6
#320000
b11000001111000010001100100011000100000001010100010000000110000011110000011000000111001 7
b1000110 6
#330000
b0 !
b0 '
b0 )
b0 +
b0 *
b0 -
b0 ,
b0 1
b0 0
b0 /
b0 .
b0 5
b0 4
b0 3
b0 (
b0 2
b1011 #
b1011 &
b0 "
b0 %
#340000
b1011 !
b1011 '
b1 )
b1000 +
b1 *
b1011 -
b1 ,
b1000 1
b100 0
b10 /
b1 .
b1000 5
b100 4
b10 3
b1 (
b1 2
b1 "
b1 %
b11000001111000001100000011000000100000001010100010000000110000011110000011000001000010 7
b0 6
#350000
b10110 !
b10110 '
b10 )
b10000 +
b10 *
b10110 -
b10 ,
b10000 1
b1000 0
b100 /
b10 .
b10000 5
b1000 4
b100 3
b10 (
b10 2
b10 "
b10 %
b11000001111000001100000011000100100000001010100010000000110000011110000011000001000010 7
b1011 6
#360000
b1110111 !
b1110111 '
b1010111 )
b10001110 +
b1010111 *
b1110111 -
b1010111 ,
b10001110 1
b1000111 0
b10101110 /
b1010111 .
b10001110 5
b1000111 4
b10101110 3
b1010111 (
b1010111 2
b1010111 "
b1010111 %
b11000001111000001100000011001000100000001010100010000000110000011110000011000001000010 7
b10110 6
#370000
b11101010 !
b11101010 '
b10000011 )
b1110100 +
b10000011 *
b11101010 -
b10000011 ,
b1110100 1
b111010 0
b11101 /
b10000011 .
b1110100 5
b111010 4
b11101 3
b10000011 (
b10000011 2
b10000011 "
b10000011 %
b11000001111000001101010011011100100000001010100010000000110000011110000011000001000010 7
b1110111 6
#380000
b1001111 !
b1001111 '
b11001010 )
b1010 +
b11001010 *
b1001111 -
b11001010 ,
b1010 1
b101 0
b10001111 /
b11001010 .
b1010 5
b101 4
b10001111 3
b11001010 (
b11001010 2
b11001010 "
b11001010 %
b11000001111000001110000011001100100000001010100010000000110000011110000011000001000010 7
b11101010 6
#390000
b10100011 !
b10100011 '
b11111111 )
b10111001 +
b11111111 *
b10100011 -
b11111111 ,
b10111001 1
b11010001 0
b11100101 /
b11111111 .
b10111001 5
b11010001 4
b11100101 3
b11111111 (
b11111111 2
b11111111 "
b11111111 %
b11000001111000010000110100000100100000001010100010000000110000011110000011000001000010 7
b1001111 6
#400000
b11000001111000010001100100011000100000001010100010000000110000011110000011000001000010 7
b10100011 6
#410000
b0 !
b0 '
b0 )
b0 +
b0 *
b0 -
b0 ,
b0 1
b0 0
b0 /
b0 .
b0 5
b0 4
b0 3
b0 (
b0 2
b1101 #
b1101 &
b0 "
b0 %
#420000
b1101 !
b1101 '
b1 )
b1000 +
b1 *
b1011 -
b1 ,
b1000 1
b100 0
b10 /
b1 .
b1000 5
b100 4
b10 3
b1 (
b1 2
b1 "
b1 %
b11000001111000001100000011000000100000001010100010000000110000011110000011000001000100 7
b0 6
#430000
b11010 !
b11010 '
b10 )
b10000 +
b10 *
b10110 -
b10 ,
b10000 1
b1000 0
b100 /
b10 .
b10000 5
b1000 4
b100 3
b10 (
b10 2
b10 "
b10 %
b11000001111000001100000011000100100000001010100010000000110000011110000011000001000100 7
b1101 6
#440000
b10011110 !
b10011110 '
b1010111 )
b10001110 +
b1010111 *
b1110111 -
b1010111 ,
b10001110 1
b1000111 0
b10101110 /
b1010111 .
b10001110 5
b1000111 4
b10101110 3
b1010111 (
b1010111 2
b1010111 "
b1010111 %
b11000001111000001100000011001000100000001010100010000000110000011110000011000001000100 7
b11010 6
#450000
b11001101 !
b11001101 '
b10000011 )
b1110100 +
b10000011 *
b11101010 -
b10000011 ,
b1110100 1
b111010 0
b11101 /
b10000011 .
b1110100 5
b111010 4
b11101 3
b10000011 (
b10000011 2
b10000011 "
b10000011 %
b11000001111000001101010011011100100000001010100010000000110000011110000011000001000100 7
b10011110 6
#460000
b11000101 !
b11000101 '
b11001010 )
b1010 +
b11001010 *
b1001111 -
b11001010 ,
b1010 1
b101 0
b10001111 /
b11001010 .
b1010 5
b101 4
b10001111 3
b11001010 (
b11001010 2
b11001010 "
b11001010 %
b11000001111000001110000011001100100000001010100010000000110000011110000011000001000100 7
b11001101 6
#470000
b10010111 !
b10010111 '
b11111111 )
b10111001 +
b11111111 *
b10100011 -
b11111111 ,
b10111001 1
b11010001 0
b11100101 /
b11111111 .
b10111001 5
b11010001 4
b11100101 3
b11111111 (
b11111111 2
b11111111 "
b11111111 %
b11000001111000010000110100000100100000001010100010000000110000011110000011000001000100 7
b11000101 6
#480000
b11000001111000010001100100011000100000001010100010000000110000011110000011000001000100 7
b10010111 6
#490000
b0 !
b0 '
b0 )
b0 +
b0 *
b0 -
b0 ,
b0 1
b0 0
b0 /
b0 .
b0 5
b0 4
b0 3
b0 (
b0 2
b1110 #
b1110 &
b0 "
b0 %
#500000
b1110 !
b1110 '
b1 )
b1000 +
b1 *
b1011 -
b1 ,
b1000 1
b100 0
b10 /
b1 .
b1000 5
b100 4
b10 3
b1 (
b1 2
b1 "
b1 %
b11000001111000001100000011000000100000001010100010000000110000011110000011000001000101 7
b0 6
#510000
b11100 !
b11100 '
b10 )
b10000 +
b10 *
b10110 -
b10 ,
b10000 1
b1000 0
b100 /
b10 .
b10000 5
b1000 4
b100 3
b10 (
b10 2
b10 "
b10 %
b11000001111000001100000011000100100000001010100010000000110000011110000011000001000101 7
b1110 6
#520000
b1100111 !
b1100111 '
b1010111 )
b10001110 +
b1010111 *
b1110111 -
b1010111 ,
b10001110 1
b1000111 0
b10101110 /
b1010111 .
b10001110 5
b1000111 4
b10101110 3
b1010111 (
b1010111 2
b1010111 "
b1010111 %
b11000001111000001100000011001000100000001010100010000000110000011110000011000001000101 7
b11100 6
#530000
b1010011 !
b1010011 '
b10000011 )
b1110100 +
b10000011 *
b11101010 -
b10000011 ,
b1110100 1
b111010 0
b11101 /
b10000011 .
b1110100 5
b111010 4
b11101 3
b10000011 (
b10000011 2
b10000011 "
b10000011 %
b11000001111000001101010011011100100000001010100010000000110000011110000011000001000101 7
b1100111 6
#540000
b10000000 !
b10000000 '
b11001010 )
b1010 +
b11001010 *
b1001111 -
b11001010 ,
b1010 1
b101 0
b10001111 /
b11001010 .
b1010 5
b101 4
b10001111 3
b11001010 (
b11001010 2
b11001010 "
b11001010 %
b11000001111000001110000011001100100000001010100010000000110000011110000011000001000101 7
b1010011 6
#550000
b10001101 !
b10001101 '
b11111111 )
b10111001 +
b11111111 *
b10100011 -
b11111111 ,
b10111001 1
b11010001 0
b11100101 /
b11111111 .
b10111001 5
b11010001 4
b11100101 3
b11111111 (
b11111111 2
b11111111 "
b11111111 %
b11000001111000010000110100000100100000001010100010000000110000011110000011000001000101 7
b10000000 6
#560000
b11000001111000010001100100011000100000001010100010000000110000011110000011000001000101 7
b10001101 6
#570000
b10110011 !
b10110011 '
b11010100 )
b11111010 +
b11010100 *
b10011101 -
b11010100 ,
b11111010 1
b1111101 0
b10110011 /
b11010100 .
b11111010 5
b1111101 4
b10110011 3
b11010100 (
b11010100 2
b10 #
b10 &
b11010100 "
b11010100 %
#580000
b11011010 !
b11011010 '
b10111111 )
b10001111 +
b10111111 *
b1010101 -
b10111111 ,
b10001111 1
b11001010 0
b1100101 /
b10111111 .
b10001111 5
b11001010 4
b1100101 3
b10111111 (
b10111111 2
b11 #
b11 &
b10111111 "
b10111111 %
#600000
b10010111 !
b10010111 '
b11111111 )
b10111001 +
b11111111 *
b10100011 -
b11111111 ,
b10111001 1
b11010001 0
b11100101 /
b11111111 .
b10111001 5
b11010001 4
b11100101 3
b11111111 (
b11111111 2
b1101 #
b1101 &
b11111111 "
b11111111 %
#610000
b10001101 !
b10001101 '
b1110 #
b1110 &
b11000001111000010001100100011000100000001010100010000000110000011110000011000001000100 7
b10010111 6
#620000
b0 !
b0 '
b1010111 )
b10001110 +
b1010111 *
b1110111 -
b1010111 ,
b10001110 1
b1000111 0
b10101110 /
b1010111 .
b10001110 5
b1000111 4
b10101110 3
b1010111 (
b1010111 2
b111 #
b111 &
b1010111 "
b1010111 %
b11000001111000010001100100011000100000001010100010000000110000011110000011000001000101 7
b10001101 6
