rtl/RTL/aes256_round_controller.v
//==============================================================================
// File: aes256_round_controller.v
// Description: Round Controller FSM for AES-256
// - Controls 14 encryption/decryption rounds
// - Manages state transitions and round counter
// - Generates control signals for datapath
//==============================================================================

module aes256_round_controller (
    input  wire        clk,
    input  wire        rst_n,
    input  wire        start_i,       // Start encryption/decryption
    input  wire        mode_i,        // 0=Encrypt, 1=Decrypt
    input  wire        key_exp_done_i,// Key expansion complete
    output reg  [3:0]  round_num_o,   // Current round number (0-14)
    output reg         busy_o,        // Core is busy
    output reg         valid_o,       // Output is valid
    output reg         load_input_o,  // Load plaintext/ciphertext
    output reg         apply_subbytes_o,
    output reg         apply_shiftrows_o,
    output reg         apply_mixcolumns_o,
    output reg         apply_addroundkey_o
);

    //==========================================================================
    // FSM STATES
    //==========================================================================
    localparam [3:0] IDLE         = 4'b0000;
    localparam [3:0] WAIT_KEY     = 4'b0001;
    localparam [3:0] LOAD_DATA    = 4'b0010;
    localparam [3:0] ROUND_0      = 4'b0011;
    localparam [3:0] ROUND_1_13   = 4'b0100;
    localparam [3:0] ROUND_14     = 4'b0101;
    localparam [3:0] OUTPUT       = 4'b0110;

    reg [3:0] state, next_state;
    reg [3:0] round_count;

    //==========================================================================
    // STATE REGISTER
    //==========================================================================
    always @(posedge clk or negedge rst_n) begin
        if (!rst_n) begin
            state <= IDLE;
        end else begin
            state <= next_state;
        end
    end

    //==========================================================================
    // NEXT STATE LOGIC
    //==========================================================================
    always @(*) begin
        next_state = state;
        
        case (state)
            IDLE: begin
                if (start_i)
                    next_state = WAIT_KEY;
            end

            WAIT_KEY: begin
                if (key_exp_done_i)
                    next_state = LOAD_DATA;
            end

            LOAD_DATA: begin
                next_state = ROUND_0;
            end

            ROUND_0: begin
                next_state = ROUND_1_13;
            end

            ROUND_1_13: begin
                if (round_count >= 12)  // After round 13 (count=12), go to round 14
                    next_state = ROUND_14;
            end

            ROUND_14: begin
                next_state = OUTPUT;
            end

            OUTPUT: begin
                if (!start_i)
                    next_state = IDLE;
            end

            default: next_state = IDLE;
        endcase
    end

    //==========================================================================
    // ROUND COUNTER
    //==========================================================================
    always @(posedge clk or negedge rst_n) begin
        if (!rst_n) begin
            round_count <= 4'd0;
        end else begin
            case (state)
                IDLE: begin
                    round_count <= 4'd0;
                end

                ROUND_0: begin
                    round_count <= 4'd0;
                end

                ROUND_1_13: begin
                    if (round_count < 13)
                        round_count <= round_count + 1'b1;
                end

                ROUND_14: begin
                    round_count <= 4'd14;
                end

                default: begin
                    round_count <= round_count;
                end
            endcase
        end
    end

    //==========================================================================
    // OUTPUT LOGIC (COMBINATIONAL for zero-delay control)
    //==========================================================================
    always @(*) begin
        // Default values
        busy_o = 1'b0;
        valid_o = 1'b0;
        load_input_o = 1'b0;
        apply_subbytes_o = 1'b0;
        apply_shiftrows_o = 1'b0;
        apply_mixcolumns_o = 1'b0;
        apply_addroundkey_o = 1'b0;
        round_num_o = 4'd0;

        case (state)
            IDLE: begin
                busy_o = 1'b0;
                valid_o = 1'b0;
                round_num_o = 4'd0;
            end

            WAIT_KEY: begin
                busy_o = 1'b1;
                valid_o = 1'b0;
            end

            LOAD_DATA: begin
                load_input_o = 1'b1;
                busy_o = 1'b1;
                valid_o = 1'b0;
            end

            ROUND_0: begin
                // Round 0: Only AddRoundKey
                apply_addroundkey_o = 1'b1;
                round_num_o = mode_i ? 4'd14 : 4'd0;  // Decrypt starts with key[14]
                busy_o = 1'b1;
                valid_o = 1'b0;
            end

            ROUND_1_13: begin
                // Rounds 1-13
                if (mode_i) begin
                    // Decryption order: InvShiftRows → InvSubBytes → AddRoundKey → InvMixColumns
                    apply_subbytes_o = 1'b1;
                    apply_shiftrows_o = 1'b1;
                    apply_addroundkey_o = 1'b1;
                    apply_mixcolumns_o = 1'b1;
                    round_num_o = 4'd13 - round_count;  // Keys: 13, 12, ..., 1 for rounds 1-13
                end else begin
                    // Encryption order: SubBytes → ShiftRows → MixColumns → AddRoundKey
                    apply_subbytes_o = 1'b1;
                    apply_shiftrows_o = 1'b1;
                    apply_mixcolumns_o = 1'b1;
                    apply_addroundkey_o = 1'b1;
                    round_num_o = round_count + 1;  // Keys: 1, 2, ..., 13 for rounds 1-13
                end
                busy_o = 1'b1;
                valid_o = 1'b0;
            end

            ROUND_14: begin
                // Final round: No MixColumns
                if (mode_i) begin
                    // Decryption: InvShiftRows → InvSubBytes → AddRoundKey
                    apply_shiftrows_o = 1'b1;
                    apply_subbytes_o = 1'b1;
                    apply_addroundkey_o = 1'b1;
                    round_num_o = 4'd0;  // Final decrypt uses key[0]
                end else begin
                    // Encryption: SubBytes → ShiftRows → AddRoundKey
                    apply_subbytes_o = 1'b1;
                    apply_shiftrows_o = 1'b1;
                    apply_addroundkey_o = 1'b1;
                    round_num_o = 4'd14;  // Final encrypt uses key[14]
                end
                busy_o = 1'b1;
                valid_o = 1'b0;
            end

            OUTPUT: begin
                busy_o = 1'b0;
                valid_o = 1'b1;
                round_num_o = 4'd0;
            end

            default: begin
                busy_o = 1'b0;
                valid_o = 1'b0;
                round_num_o = 4'd0;
            end
        endcase
    end

endmodule

rtl/tb_aes256/tb_aes256_round_controller.v
//==============================================================================
// Simplified Functional Testbench for AES-256 Round Controller
// Focus: Basic functionality, not cycle-accurate timing
//==============================================================================

`timescale 1ns / 1ps

module tb_round_controller_simple;

    reg clk, rst_n, start_i, mode_i, key_exp_done_i;
    wire [3:0] round_num_o;
    wire busy_o, valid_o;
    wire load_input_o, apply_subbytes_o, apply_shiftrows_o, apply_mixcolumns_o, apply_addroundkey_o;

    integer errors = 0;
    integer test_count = 0;

    aes256_round_controller dut (
        .clk(clk),
        .rst_n(rst_n),
        .start_i(start_i),
        .mode_i(mode_i),
        .key_exp_done_i(key_exp_done_i),
        .round_num_o(round_num_o),
        .busy_o(busy_o),
        .valid_o(valid_o),
        .load_input_o(load_input_o),
        .apply_subbytes_o(apply_subbytes_o),
        .apply_shiftrows_o(apply_shiftrows_o),
        .apply_mixcolumns_o(apply_mixcolumns_o),
        .apply_addroundkey_o(apply_addroundkey_o)
    );

    initial clk = 0;
    always #5 clk = ~clk;

    initial begin
        $dumpfile("tb_round_controller_simple.vcd");
        $dumpvars(0, tb_round_controller_simple);

        rst_n = 0;
        start_i = 0;
        mode_i = 0;
        key_exp_done_i = 0;
        #30;
        rst_n = 1;
        #10;

        // TEST 1: Basic encryption flow
        test_count = test_count + 1;
        $display("\n========================================");
        $display("Test 1: Basic Encryption Flow");
        $display("========================================");
        
        start_i = 1;
        mode_i = 0;
        key_exp_done_i = 1;
        
        // Wait for busy
        repeat(5) @(posedge clk);
        if (busy_o !== 1) begin
            $display("ERROR: busy not asserted");
            errors = errors + 1;
        end else begin
            $display("PASS: Controller is busy");
        end
        
        // Wait for completion
        wait(valid_o == 1);
        $display("PASS: Encryption completed, valid=1");
        
        if (busy_o !== 0) begin
            $display("ERROR: busy should be 0 when valid");
            errors = errors + 1;
        end
        
        start_i = 0;
        @(posedge clk);
        @(posedge clk);
        
        // TEST 2: Decryption flow
        test_count = test_count + 1;
        $display("\n========================================");
        $display("Test 2: Basic Decryption Flow");
        $display("========================================");
        
        start_i = 1;
        mode_i = 1;  // Decrypt
        key_exp_done_i = 1;
        
        repeat(5) @(posedge clk);
        if (busy_o !== 1) begin
            $display("ERROR: busy not asserted for decrypt");
            errors = errors + 1;
        end else begin
            $display("PASS: Controller is busy (decrypt mode)");
        end
        
        wait(valid_o == 1);
        $display("PASS: Decryption completed, valid=1");
        
        start_i = 0;
        @(posedge clk);
        @(posedge clk);
        
        // TEST 3: Reset during operation
        test_count = test_count + 1;
        $display("\n========================================");
        $display("Test 3: Reset During Operation");
        $display("========================================");
        
        start_i = 1;
        mode_i = 0;
        key_exp_done_i = 1;
        
        repeat(5) @(posedge clk);
        
        rst_n = 0;
        @(posedge clk);
        @(posedge clk);
        
        if (busy_o !== 0 || valid_o !== 0) begin
            $display("ERROR: Outputs not reset");
            errors = errors + 1;
        end else begin
            $display("PASS: Reset clears all outputs");
        end
        
        rst_n = 1;
        start_i = 0;
        @(posedge clk);
        
        // SUMMARY
        $display("\n========================================");
        $display("TEST SUMMARY");
        $display("========================================");
        $display("Total tests: %0d", test_count);
        $display("Total errors: %0d", errors);
        
        if (errors == 0) begin
            $display("\n*** ALL TESTS PASSED ***\n");
        end else begin
            $display("\n*** %0d ERRORS FOUND ***\n", errors);
        end
        
        $finish;
    end

endmodule

rtl/gtkwave/tb_aes256_round_controller.vcd
$date
	Fri Oct 31 13:30:34 2025
$end
$version
	Icarus Verilog
$end
$timescale
	1ps
$end
$scope module tb_round_controller_simple $end
$var wire 1 ! valid_o $end
$var wire 4 " round_num_o [3:0] $end
$var wire 1 # load_input_o $end
$var wire 1 $ busy_o $end
$var wire 1 % apply_subbytes_o $end
$var wire 1 & apply_shiftrows_o $end
$var wire 1 ' apply_mixcolumns_o $end
$var wire 1 ( apply_addroundkey_o $end
$var reg 1 ) clk $end
$var reg 1 * key_exp_done_i $end
$var reg 1 + mode_i $end
$var reg 1 , rst_n $end
$var reg 1 - start_i $end
$var integer 32 . errors [31:0] $end
$var integer 32 / test_count [31:0] $end
$scope module dut $end
$var wire 1 ) clk $end
$var wire 1 * key_exp_done_i $end
$var wire 1 + mode_i $end
$var wire 1 , rst_n $end
$var wire 1 - start_i $end
$var parameter 4 0 IDLE $end
$var parameter 4 1 LOAD_DATA $end
$var parameter 4 2 OUTPUT $end
$var parameter 4 3 ROUND_0 $end
$var parameter 4 4 ROUND_14 $end
$var parameter 4 5 ROUND_1_13 $end
$var parameter 4 6 WAIT_KEY $end
$var reg 1 ( apply_addroundkey_o $end
$var reg 1 ' apply_mixcolumns_o $end
$var reg 1 & apply_shiftrows_o $end
$var reg 1 % apply_subbytes_o $end
$var reg 1 $ busy_o $end
$var reg 1 # load_input_o $end
$var reg 4 7 next_state [3:0] $end
$var reg 4 8 round_count [3:0] $end
$var reg 4 9 round_num_o [3:0] $end
$var reg 4 : state [3:0] $end
$var reg 1 ! valid_o $end
$upscope $end
$upscope $end
$enddefinitions $end
$comment Show the parameter values. $end
$dumpall
b1 6
b100 5
b101 4
b11 3
b110 2
b10 1
b0 0
$end
#0
$dumpvars
b0 :
b0 9
b0 8
b0 7
b0 /
b0 .
0-
0,
0+
0*
0)
0(
0'
0&
0%
0$
0#
b0 "
0!
$end
#5000
1)
#10000
0)
#15000
1)
#20000
0)
#25000
1)
#30000
0)
1,
#35000
1)
#40000
b1 7
0)
1*
1-
b1 /
#45000
b10 7
b1 :
1)
#50000
0)
#55000
b11 7
b10 :
1$
1)
#60000
0)
#65000
b100 7
1#
b11 :
1)
#70000
0)
#75000
b100 :
1(
0#
1)
#80000
0)
#85000
b1 "
b1 9
1'
1&
1%
1(
b1 8
1)
#90000
0)
#95000
b10 8
b10 "
b10 9
1(
1'
1&
1%
1)
#100000
0)
#105000
b11 "
b11 9
1(
1'
1&
1%
b11 8
1)
#110000
0)
#115000
b100 8
b100 "
b100 9
1(
1'
1&
1%
1)
#120000
0)
#125000
b101 "
b101 9
1(
1'
1&
1%
b101 8
1)
#130000
0)
#135000
b110 8
b110 "
b110 9
1(
1'
1&
1%
1)
#140000
0)
#145000
b111 "
b111 9
1(
1'
1&
1%
b111 8
1)
#150000
0)
#155000
b1000 8
b1000 "
b1000 9
1(
1'
1&
1%
1)
#160000
0)
#165000
b1001 "
b1001 9
1(
1'
1&
1%
b1001 8
1)
#170000
0)
#175000
b1010 8
b1010 "
b1010 9
1(
1'
1&
1%
1)
#180000
0)
#185000
b1011 "
b1011 9
1(
1'
1&
1%
b1011 8
1)
#190000
0)
#195000
b1100 8
b1100 "
b1100 9
1(
1'
1&
1%
1)
#200000
0)
#205000
b101 7
b1101 "
b1101 9
1(
1'
1&
1%
b1101 8
1)
#210000
0)
#215000
b110 7
b101 :
b1110 "
b1110 9
1(
1'
1&
1%
1)
#220000
0)
#225000
1(
0'
1&
1%
b1110 8
b110 :
1)
#230000
0)
#235000
b0 7
0-
b0 "
b0 9
1!
0$
0(
0&
0%
1)
#240000
0)
#245000
b0 :
1)
#250000
0)
#255000
b0 8
0!
b1 7
1+
1-
b10 /
1)
#260000
0)
#265000
b10 7
b1 :
1)
#270000
0)
#275000
b11 7
b10 :
1$
1)
#280000
0)
#285000
b100 7
1#
b11 :
1)
#290000
0)
#295000
b100 :
b1110 "
b1110 9
1(
0#
1)
#300000
0)
#305000
1'
1&
1%
1(
b1 8
1)
#310000
0)
#315000
b10 8
b1101 "
b1101 9
1(
1'
1&
1%
1)
#320000
0)
#325000
b1100 "
b1100 9
1(
1'
1&
1%
b11 8
1)
#330000
0)
#335000
b100 8
b1011 "
b1011 9
1(
1'
1&
1%
1)
#340000
0)
#345000
b1010 "
b1010 9
1(
1'
1&
1%
b101 8
1)
#350000
0)
#355000
b110 8
b1001 "
b1001 9
1(
1'
1&
1%
1)
#360000
0)
#365000
b1000 "
b1000 9
1(
1'
1&
1%
b111 8
1)
#370000
0)
#375000
b1000 8
b111 "
b111 9
1(
1'
1&
1%
1)
#380000
0)
#385000
b110 "
b110 9
1(
1'
1&
1%
b1001 8
1)
#390000
0)
#395000
b1010 8
b101 "
b101 9
1(
1'
1&
1%
1)
#400000
0)
#405000
b100 "
b100 9
1(
1'
1&
1%
b1011 8
1)
#410000
0)
#415000
b1100 8
b11 "
b11 9
1(
1'
1&
1%
1)
#420000
0)
#425000
b101 7
b10 "
b10 9
1(
1'
1&
1%
b1101 8
1)
#430000
0)
#435000
b110 7
b101 :
b1 "
b1 9
1(
1'
1&
1%
1)
#440000
0)
#445000
b0 "
b0 9
1(
0'
1&
1%
b1110 8
b110 :
1)
#450000
0)
#455000
b0 7
0-
1!
0$
0(
0&
0%
1)
#460000
0)
#465000
b0 :
1)
#470000
0)
#475000
b0 8
0!
b1 7
0+
1-
b11 /
1)
#480000
0)
#485000
b10 7
b1 :
1)
#490000
0)
#495000
b11 7
b10 :
1$
1)
#500000
0)
#505000
b100 7
1#
b11 :
1)
#510000
0)
#515000
b100 :
1(
0#
1)
#520000
0)
#525000
b1 7
0(
0$
b0 :
0,
1)
#530000
0)
#535000
1)
#540000
0)
#545000
b1 :
b10 7
0-
1,
1)
#550000
0)
#555000
b11 7
b10 :
1$
1)
